zephyr_rtos_ai/__about__.py
zephyr_rtos_ai/__init__.py
zephyr_rtos_ai-0.0.1.dist-info/METADATA
zephyr_rtos_ai-0.0.1.dist-info/WHEEL
zephyr_rtos_ai-0.0.1.dist-info/entry_points.txt
zephyr_rtos_ai-0.0.1.dist-info/licenses/LICENSE
zephyr_rtos_ai-0.0.1.dist-info/RECORD
