Metadata-Version: 2.4
Name: zephyr-rtos-ai
Version: 0.0.1
Summary: A collection of tools and libraries for working with Zephyr RTOS
Project-URL: repository, https://github.com/ksachdeva/ditto-client
Author: Sachdeva, Kapil
License-File: LICENSE
Classifier: Intended Audience :: Developers
Classifier: License :: OSI Approved :: Apache Software License
Classifier: Operating System :: OS Independent
Classifier: Programming Language :: Python
Classifier: Programming Language :: Python :: 3
Classifier: Programming Language :: Python :: 3.11
Classifier: Programming Language :: Python :: 3.12
Classifier: Programming Language :: Python :: 3.13
Classifier: Programming Language :: Python :: 3.14
Classifier: Topic :: Software Development :: Libraries :: Python Modules
Requires-Python: >=3.11
